{".class": "MypyFile", "_fullname": "igem.server.etl.prepare", "future_import_flags": [], "is_partial_stub_package": false, "is_stub": false, "names": {".class": "SymbolTable", "Connector": {".class": "SymbolTableNode", "kind": "Gdef", "node": {".class": "Var", "flags": ["is_suppressed_import", "is_ready", "is_inferred"], "fullname": "igem.server.etl.prepare.Connector", "name": "Connector", "type": {".class": "AnyType", "missing_import_name": "igem.server.etl.prepare.Connector", "source_any": null, "type_of_any": 3}}}, "DSTColumn": {".class": "SymbolTableNode", "kind": "Gdef", "node": {".class": "Var", "flags": ["is_suppressed_import", "is_ready", "is_inferred"], "fullname": "igem.server.etl.prepare.DSTColumn", "name": "DSTColumn", "type": {".class": "AnyType", "missing_import_name": "igem.server.etl.prepare.DSTColumn", "source_any": null, "type_of_any": 3}}}, "ObjectDoesNotExist": {".class": "SymbolTableNode", "kind": "Gdef", "node": {".class": "Var", "flags": ["is_suppressed_import", "is_ready", "is_inferred"], "fullname": "igem.server.etl.prepare.ObjectDoesNotExist", "name": "ObjectDoesNotExist", "type": {".class": "AnyType", "missing_import_name": "igem.server.etl.prepare.ObjectDoesNotExist", "source_any": null, "type_of_any": 3}}}, "ThreadPoolExecutor": {".class": "SymbolTableNode", "kind": "Gdef", "node": {".class": "Var", "flags": ["is_suppressed_import", "is_ready", "is_inferred"], "fullname": "igem.server.etl.prepare.ThreadPoolExecutor", "name": "ThreadPoolExecutor", "type": {".class": "AnyType", "missing_import_name": "igem.server.etl.prepare.ThreadPoolExecutor", "source_any": null, "type_of_any": 3}}}, "WFControl": {".class": "SymbolTableNode", "kind": "Gdef", "node": {".class": "Var", "flags": ["is_suppressed_import", "is_ready", "is_inferred"], "fullname": "igem.server.etl.prepare.WFControl", "name": "WFControl", "type": {".class": "AnyType", "missing_import_name": "igem.server.etl.prepare.WFControl", "source_any": null, "type_of_any": 3}}}, "WordTerm": {".class": "SymbolTableNode", "kind": "Gdef", "node": {".class": "Var", "flags": ["is_suppressed_import", "is_ready", "is_inferred"], "fullname": "igem.server.etl.prepare.WordTerm", "name": "WordTerm", "type": {".class": "AnyType", "missing_import_name": "igem.server.etl.prepare.WordTerm", "source_any": null, "type_of_any": 3}}}, "__annotations__": {".class": "SymbolTableNode", "kind": "Gdef", "node": {".class": "Var", "flags": ["is_ready"], "fullname": "igem.server.etl.prepare.__annotations__", "name": "__annotations__", "type": {".class": "Instance", "args": ["builtins.str", {".class": "AnyType", "missing_import_name": null, "source_any": null, "type_of_any": 6}], "type_ref": "builtins.dict"}}}, "__doc__": {".class": "SymbolTableNode", "kind": "Gdef", "node": {".class": "Var", "flags": ["is_ready"], "fullname": "igem.server.etl.prepare.__doc__", "name": "__doc__", "type": "builtins.str"}}, "__file__": {".class": "SymbolTableNode", "kind": "Gdef", "node": {".class": "Var", "flags": ["is_ready"], "fullname": "igem.server.etl.prepare.__file__", "name": "__file__", "type": "builtins.str"}}, "__name__": {".class": "SymbolTableNode", "kind": "Gdef", "node": {".class": "Var", "flags": ["is_ready"], "fullname": "igem.server.etl.prepare.__name__", "name": "__name__", "type": "builtins.str"}}, "__package__": {".class": "SymbolTableNode", "kind": "Gdef", "node": {".class": "Var", "flags": ["is_ready"], "fullname": "igem.server.etl.prepare.__package__", "name": "__package__", "type": "builtins.str"}}, "as_completed": {".class": "SymbolTableNode", "cross_ref": "concurrent.futures._base.as_completed", "kind": "Gdef"}, "df_mapping": {".class": "SymbolTableNode", "kind": "Gdef", "node": {".class": "Var", "flags": ["is_inferred", "has_explicit_value"], "fullname": "igem.server.etl.prepare.df_mapping", "name": "df_mapping", "type": {".class": "AnyType", "missing_import_name": "igem.server.etl.prepare.pd", "source_any": {".class": "AnyType", "missing_import_name": "igem.server.etl.prepare.pd", "source_any": null, "type_of_any": 3}, "type_of_any": 7}}}, "logger": {".class": "SymbolTableNode", "kind": "Gdef", "node": {".class": "Var", "flags": ["is_suppressed_import", "is_ready", "is_inferred"], "fullname": "igem.server.etl.prepare.logger", "name": "logger", "type": {".class": "AnyType", "missing_import_name": "igem.server.etl.prepare.logger", "source_any": null, "type_of_any": 3}}}, "np": {".class": "SymbolTableNode", "cross_ref": "numpy", "kind": "Gdef"}, "os": {".class": "SymbolTableNode", "cross_ref": "os", "kind": "Gdef"}, "pd": {".class": "SymbolTableNode", "kind": "Gdef", "node": {".class": "Var", "flags": ["is_suppressed_import", "is_ready", "is_inferred"], "fullname": "igem.server.etl.prepare.pd", "name": "pd", "type": {".class": "AnyType", "missing_import_name": "igem.server.etl.prepare.pd", "source_any": null, "type_of_any": 3}}}, "prepare": {".class": "SymbolTableNode", "kind": "Gdef", "node": {".class": "FuncDef", "abstract_status": 0, "arg_kinds": [1, 1], "arg_names": ["connector", "chunk"], "flags": [], "fullname": "igem.server.etl.prepare.prepare", "name": "prepare", "type": {".class": "CallableType", "arg_kinds": [1, 1], "arg_names": ["connector", "chunk"], "arg_types": [{".class": "AnyType", "missing_import_name": null, "source_any": null, "type_of_any": 1}, {".class": "AnyType", "missing_import_name": null, "source_any": null, "type_of_any": 1}], "bound_args": [], "def_extras": {"first_arg": null}, "fallback": "builtins.function", "from_concatenate": false, "implicit": false, "is_ellipsis_args": false, "name": "prepare", "ret_type": "builtins.bool", "type_guard": null, "unpack_kwargs": false, "variables": []}}}, "re": {".class": "SymbolTableNode", "cross_ref": "re", "kind": "Gdef"}, "search_engine": {".class": "SymbolTableNode", "kind": "Gdef", "node": {".class": "FuncDef", "abstract_status": 0, "arg_kinds": [0, 0, 0], "arg_names": ["lines", "log", "connector"], "flags": [], "fullname": "igem.server.etl.prepare.search_engine", "name": "search_engine", "type": null}}, "settings": {".class": "SymbolTableNode", "kind": "Gdef", "node": {".class": "Var", "flags": ["is_suppressed_import", "is_ready", "is_inferred"], "fullname": "igem.server.etl.prepare.settings", "name": "settings", "type": {".class": "AnyType", "missing_import_name": "igem.server.etl.prepare.settings", "source_any": null, "type_of_any": 3}}}, "start_logger": {".class": "SymbolTableNode", "kind": "Gdef", "node": {".class": "Var", "flags": ["is_suppressed_import", "is_ready", "is_inferred"], "fullname": "igem.server.etl.prepare.start_logger", "name": "start_logger", "type": {".class": "AnyType", "missing_import_name": "igem.server.etl.prepare.start_logger", "source_any": null, "type_of_any": 3}}}, "sys": {".class": "SymbolTableNode", "cross_ref": "sys", "kind": "Gdef"}, "time": {".class": "SymbolTableNode", "cross_ref": "time", "kind": "Gdef"}, "timezone": {".class": "SymbolTableNode", "kind": "Gdef", "node": {".class": "Var", "flags": ["is_suppressed_import", "is_ready", "is_inferred"], "fullname": "igem.server.etl.prepare.timezone", "name": "timezone", "type": {".class": "AnyType", "missing_import_name": "igem.server.etl.prepare.timezone", "source_any": null, "type_of_any": 3}}}, "warnings": {".class": "SymbolTableNode", "cross_ref": "warnings", "kind": "Gdef"}, "x": {".class": "SymbolTableNode", "kind": "Gdef", "node": {".class": "Var", "flags": ["is_inferred", "has_explicit_value"], "fullname": "igem.server.etl.prepare.x", "name": "x", "type": "builtins.str"}}}, "path": "/Users/andrerico/DEV/projects/igem/igem_sandbox/igem/server/etl/prepare.py"}